odoo/addons/stock_orderpoint_route/README.rst
odoo/addons/stock_orderpoint_route/__init__.py
odoo/addons/stock_orderpoint_route/__manifest__.py
odoo/addons/stock_orderpoint_route/i18n/stock_orderpoint_route.pot
odoo/addons/stock_orderpoint_route/models/__init__.py
odoo/addons/stock_orderpoint_route/models/stock_warehouse_orderpoint.py
odoo/addons/stock_orderpoint_route/readme/CONTRIBUTORS.rst
odoo/addons/stock_orderpoint_route/readme/CREDITS.rst
odoo/addons/stock_orderpoint_route/readme/DESCRIPTION.rst
odoo/addons/stock_orderpoint_route/readme/USAGE.rst
odoo/addons/stock_orderpoint_route/static/description/icon.png
odoo/addons/stock_orderpoint_route/static/description/index.html
odoo/addons/stock_orderpoint_route/tests/__init__.py
odoo/addons/stock_orderpoint_route/tests/test_stock_orderpoint_route.py
odoo/addons/stock_orderpoint_route/views/stock_warehouse_orderpoint_views.xml
odoo14_addon_stock_orderpoint_route-14.0.1.1.1.dist-info/METADATA
odoo14_addon_stock_orderpoint_route-14.0.1.1.1.dist-info/WHEEL
odoo14_addon_stock_orderpoint_route-14.0.1.1.1.dist-info/top_level.txt
odoo14_addon_stock_orderpoint_route-14.0.1.1.1.dist-info/RECORD
